connect_mydb/__init__.py
connect_mydb/core.py
connect_mydb-0.1.1.dist-info/licenses/LICENSE
tests/__init__.py
tests/test_connect.py
connect_mydb-0.1.1.dist-info/METADATA
connect_mydb-0.1.1.dist-info/WHEEL
connect_mydb-0.1.1.dist-info/top_level.txt
connect_mydb-0.1.1.dist-info/RECORD
