Metadata-Version: 2.4
Name: connect-mydb
Version: 0.1.1
Summary: A lightweight Python package that helps you connect to a MySQL database with a single line of code
Home-page: https://github.com/k3XD16/connect-mydb
Author: Mohamed Khasim
Classifier: Programming Language :: Python :: 3
Classifier: License :: OSI Approved :: MIT License
Classifier: Operating System :: OS Independent
Requires-Python: >=3.7
License-File: LICENSE
Requires-Dist: mysql-connector-python
Dynamic: author
Dynamic: classifier
Dynamic: description
Dynamic: description-content-type
Dynamic: home-page
Dynamic: license-file
Dynamic: requires-dist
Dynamic: requires-python
Dynamic: summary
